Vivado-Project/NeuralNetwork/NeuralNetwork.srcs/sources_1/imports/keras_NN/linear.sv
module linear(
    input [19:0] x,
    output reg signed [15:0] y
  );

  //4 MSB's are not used as input should never exceed 0xFFFF
  assign y = x[15:0];

endmodule

System-Verilog-Files/neuron_linear.sv
module NEURON_LIN #(
    parameter SIG_SIZE = 16,
    parameter WEIGHT_SIZE = 16,
    parameter ADDITION_SIZE = 20,
    parameter NUM_INPUTS = 3
  )(
    input signed [SIG_SIZE-1:0] NEURON_IN[NUM_INPUTS-1:0],
    input signed [WEIGHT_SIZE-1:0] WEIGHTS_IN[NUM_INPUTS-1:0],
    input WB_EN,
    input signed [WEIGHT_SIZE-1:0] BIAS_IN,
    input CLOCK_N,
    output reg signed [SIG_SIZE-1:0] NEURON_OUT
  );
  logic signed [WEIGHT_SIZE-1:0] weights[NUM_INPUTS-1:0];
  logic signed [WEIGHT_SIZE-1:0] bias;
  logic signed [SIG_SIZE*2-1:0] ixw [NUM_INPUTS-1:0];
  logic signed [ADDITION_SIZE-1:0] addition;
  logic sigmoid_flag = 0;
  integer i;

  linear activation(.x(addition),
                    .y(NEURON_OUT));

  initial
  begin
    addition <= 0;
  end

  always @(negedge CLOCK_N)
  begin
    if(WB_EN)
    begin
      for(i = 0; i<NUM_INPUTS;i++)
      begin
        weights[i] <= WEIGHTS_IN[i];
      end
      bias <= BIAS_IN;
    end
    addition = bias;
    //multiply inputs by weights
    //add product to addition register
    for(i=0;i<NUM_INPUTS;i++)
    begin
      ixw[i] <= ((NEURON_IN[i]*weights[i])>>15);
      addition = addition + ixw[i];
      if(ixw[i] > 16'h7fff)
        addition = addition - 20'h10000;
    end
  end

endmodule

Vivado-Project/NeuralNetwork/NeuralNetwork.srcs/sources_1/new/SigmoidLUT.sv
module SIGMOID_LUT(
    input [19:0] x [9:0],
    output reg signed [15:0] y [9:0]
  );

  reg signed [15:0] lut [(2**20)-1:0];

  initial
  begin
    $readmemh("sfp.mem",lut);
  end

  always@(x[0]) y[0] <= lut[x[0]];
  always@(x[1]) y[1] <= lut[x[1]];
  always@(x[2]) y[2] <= lut[x[2]];
  always@(x[3]) y[3] <= lut[x[3]];
  always@(x[4]) y[4] <= lut[x[4]];
  always@(x[5]) y[5] <= lut[x[5]];
  always@(x[6]) y[6] <= lut[x[6]];
  always@(x[7]) y[7] <= lut[x[7]];
  always@(x[8]) y[8] <= lut[x[8]];
  always@(x[9]) y[9] <= lut[x[9]];

endmodule

System-Verilog-Files/neuron_redo.sv
module NEURON #(
    parameter SIG_SIZE = 16,
    parameter WEIGHT_SIZE = 16,
    parameter ADDITION_SIZE = 20,
    parameter NUM_INPUTS = 3
  )(
    input signed [SIG_SIZE-1:0] NEURON_IN[NUM_INPUTS-1:0],
    input signed [WEIGHT_SIZE-1:0] WEIGHTS_IN[NUM_INPUTS-1:0],
    input WB_EN,
    input signed [WEIGHT_SIZE-1:0] BIAS_IN,
    input CLOCK_N,
    output reg signed [ADDITION_SIZE-1:0] NEURON_OUT
  );
  logic signed [WEIGHT_SIZE-1:0] weights[NUM_INPUTS-1:0];
  logic signed [WEIGHT_SIZE-1:0] bias;
  logic signed [SIG_SIZE*2-1:0] ixw [NUM_INPUTS-1:0];
  logic signed [ADDITION_SIZE-1:0] addition;
  integer i;

  assign NEURON_OUT = addition;

  initial
  begin
    addition <= 0;
  end

  always @(negedge CLOCK_N)
  begin
    if(WB_EN)
    begin
      for(i = 0; i<NUM_INPUTS;i++)
      begin
        weights[i] <= WEIGHTS_IN[i];
      end
      bias <= BIAS_IN;
    end
    addition = bias;
    //multiply inputs by weights
    //add product to addition register
    for(i=0;i<NUM_INPUTS;i++)
    begin
      ixw[i] <= ((NEURON_IN[i]*weights[i])>>15);
      addition = addition + ixw[i][15:0];
      if(ixw[i] > 16'h7fff)
        addition = addition - 20'h10000;
    end
  end

endmodule

Vivado-Project/NeuralNetwork/NeuralNetwork.srcs/sources_1/imports/nn/delay.sv
module DELAY#(
    parameter SIG_SIZE = 16,
    parameter WEIGHT_SIZE = 16,
    parameter ADDITION_SIZE = 32,
    parameter NUM_INPUTS = 3
  )(
    input signed [SIG_SIZE-1:0]INPUT,
    input CLK_N,
    output reg signed [SIG_SIZE-1:0]DELAY_OUTPUT
  );

  reg signed [SIG_SIZE-1:0]TEMP_HOLD;

  always @(negedge CLK_N)
  begin
    DELAY_OUTPUT <= TEMP_HOLD;
    TEMP_HOLD <= INPUT;
  end

  initial
  begin
    DELAY_OUTPUT = 0;
    TEMP_HOLD = 0;
  end

endmodule

Vivado-Project/NeuralNetwork/NeuralNetwork.srcs/sources_1/imports/nn/TDNN.sv
module TDNN#(
    parameter SIG_SIZE = 16,
    parameter WEIGHT_SIZE = 16,
    parameter ADDITION_SIZE = 20,
    parameter LAYER1_IN_SIZE = 10,
    parameter LAYER2_IN_SIZE = 10,
    parameter NUM_SIGS = 2
  )(
    input signed [SIG_SIZE-1:0] SIG_IN1,
    input signed [SIG_SIZE-1:0] SIG_IN2,
    input signed CLOCK_N,
    input signed wb_en,
    output signed [SIG_SIZE-1:0] SIG_OUT1,
    output signed [SIG_SIZE-1:0] SIG_OUT2
  );
  wire signed [SIG_SIZE-1:0] delay_out_1;
  wire signed [SIG_SIZE-1:0] delay_out_2;
  wire signed [SIG_SIZE-1:0] delay_out_3;
  wire signed [SIG_SIZE-1:0] delay_out_4;
  wire signed [SIG_SIZE-1:0] delay_out_5;
  wire signed [SIG_SIZE-1:0] delay_out_6;
  wire signed [SIG_SIZE-1:0] delay_out_7;
  wire signed [SIG_SIZE-1:0] delay_out_8;

  wire signed [ADDITION_SIZE-1:0] n1_out;
  wire signed [ADDITION_SIZE-1:0] n2_out;
  wire signed [ADDITION_SIZE-1:0] n3_out;
  wire signed [ADDITION_SIZE-1:0] n4_out;
  wire signed [ADDITION_SIZE-1:0] n5_out;
  wire signed [ADDITION_SIZE-1:0] n6_out;
  wire signed [ADDITION_SIZE-1:0] n7_out;
  wire signed [ADDITION_SIZE-1:0] n8_out;
  wire signed [ADDITION_SIZE-1:0] n9_out;
  wire signed [ADDITION_SIZE-1:0] n10_out;
  wire signed [SIG_SIZE-1:0] l1_sigmoid_out [9:0];
  wire signed [SIG_SIZE-1:0] n11_out;
  wire signed [SIG_SIZE-1:0] n12_out;

  reg signed [(WEIGHT_SIZE-1):0] WEIGHTS1 [(10*10)-1:0];
  reg signed [(WEIGHT_SIZE-1):0] WEIGHTS2 [(2*10)-1:0];

  wire signed [WEIGHT_SIZE-1:0] N1W[LAYER1_IN_SIZE-1:0];
  wire signed [WEIGHT_SIZE-1:0] N2W[LAYER1_IN_SIZE-1:0];
  wire signed [WEIGHT_SIZE-1:0] N3W[LAYER1_IN_SIZE-1:0];
  wire signed [WEIGHT_SIZE-1:0] N4W[LAYER1_IN_SIZE-1:0];
  wire signed [WEIGHT_SIZE-1:0] N5W[LAYER1_IN_SIZE-1:0];
  wire signed [WEIGHT_SIZE-1:0] N6W[LAYER1_IN_SIZE-1:0];
  wire signed [WEIGHT_SIZE-1:0] N7W[LAYER1_IN_SIZE-1:0];
  wire signed [WEIGHT_SIZE-1:0] N8W[LAYER1_IN_SIZE-1:0];
  wire signed [WEIGHT_SIZE-1:0] N9W[LAYER1_IN_SIZE-1:0];
  wire signed [WEIGHT_SIZE-1:0] N10W[LAYER1_IN_SIZE-1:0];
  wire signed [WEIGHT_SIZE-1:0] N11W[LAYER2_IN_SIZE-1:0];
  wire signed [WEIGHT_SIZE-1:0] N12W[LAYER2_IN_SIZE-1:0];


  generate
    genvar i;
    for(i=0;i<10;i++)
    begin
      assign N1W[i] = WEIGHTS1[0+i];
      assign N2W[i] = WEIGHTS1[10+i];
      assign N3W[i] = WEIGHTS1[20+i];
      assign N4W[i] = WEIGHTS1[30+i];
      assign N5W[i] = WEIGHTS1[40+i];
      assign N6W[i] = WEIGHTS1[50+i];
      assign N7W[i] = WEIGHTS1[60+i];
      assign N8W[i] = WEIGHTS1[70+i];
      assign N9W[i] = WEIGHTS1[80+i];
      assign N10W[i] = WEIGHTS1[90+i];
      assign N11W[i] = WEIGHTS2[0+i];
      assign N12W[i] = WEIGHTS2[10+i];
    end
  endgenerate

  reg signed [WEIGHT_SIZE-1:0] bias1 [9:0]; //Layer 1 bias
  reg signed [WEIGHT_SIZE-1:0] bias2 [1:0]; //Layer 2 bias

  //Delays for Sig_in_1
  DELAY delay1(SIG_IN1,CLOCK_N,delay_out_1);
  DELAY delay2(delay_out_1,CLOCK_N,delay_out_2);
  DELAY delay3(delay_out_2,CLOCK_N,delay_out_3);
  DELAY delay4(delay_out_3,CLOCK_N,delay_out_4);

  //Delays for Sig_in_2
  DELAY delay5(SIG_IN2,CLOCK_N,delay_out_5);
  DELAY delay6(delay_out_5,CLOCK_N,delay_out_6);
  DELAY delay7(delay_out_6,CLOCK_N,delay_out_7);
  DELAY delay8(delay_out_7,CLOCK_N,delay_out_8);

  //Layer 1
  NEURON #(.NUM_INPUTS(LAYER1_IN_SIZE)) neuron1(
           .NEURON_IN(
             {delay_out_8, delay_out_4, delay_out_7, delay_out_3, delay_out_6,
              delay_out_2, delay_out_5, delay_out_1, SIG_IN2, SIG_IN1}),
           .WEIGHTS_IN(N1W),
           .WB_EN(wb_en),
           .BIAS_IN(bias1[0]),
           .CLOCK_N(CLOCK_N),
           .NEURON_OUT(n1_out));
  NEURON #(.NUM_INPUTS(LAYER1_IN_SIZE)) neuron2(
           .NEURON_IN({delay_out_8, delay_out_4, delay_out_7, delay_out_3, delay_out_6,
                       delay_out_2, delay_out_5, delay_out_1, SIG_IN2, SIG_IN1}),
           .WEIGHTS_IN(N2W),
           .WB_EN(wb_en),
           .BIAS_IN(bias1[1]),
           .CLOCK_N(CLOCK_N),
           .NEURON_OUT(n2_out));
  NEURON #(.NUM_INPUTS(LAYER1_IN_SIZE)) neuron3(
           .NEURON_IN({delay_out_8, delay_out_4, delay_out_7, delay_out_3, delay_out_6,
                       delay_out_2, delay_out_5, delay_out_1, SIG_IN2, SIG_IN1}),
           .WEIGHTS_IN(N3W),
           .WB_EN(wb_en),
           .BIAS_IN(bias1[2]),
           .CLOCK_N(CLOCK_N),
           .NEURON_OUT(n3_out));
  NEURON #(.NUM_INPUTS(LAYER1_IN_SIZE)) neuron4(
           .NEURON_IN({delay_out_8, delay_out_4, delay_out_7, delay_out_3, delay_out_6,
                       delay_out_2, delay_out_5, delay_out_1, SIG_IN2, SIG_IN1}),
           .WEIGHTS_IN(N4W),
           .WB_EN(wb_en),
           .BIAS_IN(bias1[3]),
           .CLOCK_N(CLOCK_N),
           .NEURON_OUT(n4_out));
  NEURON #(.NUM_INPUTS(LAYER1_IN_SIZE)) neuron5(
           .NEURON_IN({delay_out_8, delay_out_4, delay_out_7, delay_out_3, delay_out_6,
                       delay_out_2, delay_out_5, delay_out_1, SIG_IN2, SIG_IN1}),
           .WEIGHTS_IN(N5W),
           .WB_EN(wb_en),
           .BIAS_IN(bias1[4]),
           .CLOCK_N(CLOCK_N),
           .NEURON_OUT(n5_out));
  NEURON #(.NUM_INPUTS(LAYER1_IN_SIZE)) neuron6(
           .NEURON_IN({delay_out_8, delay_out_4, delay_out_7, delay_out_3, delay_out_6,
                       delay_out_2, delay_out_5, delay_out_1, SIG_IN2, SIG_IN1}),
           .WEIGHTS_IN(N6W),
           .WB_EN(wb_en),
           .BIAS_IN(bias1[5]),
           .CLOCK_N(CLOCK_N),
           .NEURON_OUT(n6_out));
  NEURON #(.NUM_INPUTS(LAYER1_IN_SIZE)) neuron7(
           .NEURON_IN({delay_out_8, delay_out_4, delay_out_7, delay_out_3, delay_out_6,
                       delay_out_2, delay_out_5, delay_out_1, SIG_IN2, SIG_IN1}),
           .WEIGHTS_IN(N7W),
           .WB_EN(wb_en),
           .BIAS_IN(bias1[6]),
           .CLOCK_N(CLOCK_N),
           .NEURON_OUT(n7_out));
  NEURON #(.NUM_INPUTS(LAYER1_IN_SIZE)) neuron8(
           .NEURON_IN({delay_out_8, delay_out_4, delay_out_7, delay_out_3, delay_out_6,
                       delay_out_2, delay_out_5, delay_out_1, SIG_IN2, SIG_IN1}),
           .WEIGHTS_IN(N8W),
           .WB_EN(wb_en),
           .BIAS_IN(bias1[7]),
           .CLOCK_N(CLOCK_N),
           .NEURON_OUT(n8_out));
  NEURON #(.NUM_INPUTS(LAYER1_IN_SIZE)) neuron9(
           .NEURON_IN({delay_out_8, delay_out_4, delay_out_7, delay_out_3, delay_out_6,
                       delay_out_2, delay_out_5, delay_out_1, SIG_IN2, SIG_IN1}),
           .WEIGHTS_IN(N9W),
           .WB_EN(wb_en),
           .BIAS_IN(bias1[8]),
           .CLOCK_N(CLOCK_N),
           .NEURON_OUT(n9_out));
  NEURON #(.NUM_INPUTS(LAYER1_IN_SIZE)) neuron10(
           .NEURON_IN({delay_out_8, delay_out_4, delay_out_7, delay_out_3, delay_out_6,
                       delay_out_2, delay_out_5, delay_out_1, SIG_IN2, SIG_IN1}),
           .WEIGHTS_IN(N10W),
           .WB_EN(wb_en),
           .BIAS_IN(bias1[9]),
           .CLOCK_N(CLOCK_N),
           .NEURON_OUT(n10_out));

  //Layer 1 Activation
  SIGMOID_LUT sigAct(.x({n10_out,n9_out,n8_out,n7_out,n6_out,n5_out,n4_out,n3_out,n2_out,n1_out}),
                     .y(l1_sigmoid_out));

  //Layer 2
  NEURON_LIN #(.NUM_INPUTS(LAYER1_IN_SIZE)) neuron11(.NEURON_IN(l1_sigmoid_out),
             .WEIGHTS_IN(N11W),
             .WB_EN(wb_en),
             .BIAS_IN(bias2[0]),
             .CLOCK_N(CLOCK_N),
             .NEURON_OUT(SIG_OUT1));
  NEURON_LIN #(.NUM_INPUTS(LAYER1_IN_SIZE)) neuron12(.NEURON_IN(l1_sigmoid_out),
             .WEIGHTS_IN(N12W),
             .WB_EN(wb_en),
             .BIAS_IN(bias2[1]),
             .CLOCK_N(CLOCK_N),
             .NEURON_OUT(SIG_OUT2));

  initial
  begin
    $readmemh("bias1.mem", bias1);
    $readmemh("weights1.mem", WEIGHTS1);
    $readmemh("bias2.mem", bias2);
    $readmemh("weights2.mem", WEIGHTS2);
  end

endmodule

Vivado-Project/NeuralNetwork/NeuralNetwork.srcs/sim_1/new/TDNN_TB.sv
module TDNN_TB();
  reg signed [15:0] sig1, sig2;
  reg topclk;
  reg WEIGHTBIAS_EN;
  wire signed [15:0] out1, out2;


  TDNN DUT(   .SIG_IN1(sig1),
              .SIG_IN2(sig2),
              .CLOCK_N(topclk),
              .SIG_OUT1(out1),
              .SIG_OUT2(out2),
              .wb_en(WEIGHTBIAS_EN)
          );

  always #5 topclk = ~topclk;

  initial
  begin
    $dumpfile("dump.vcd");
    $dumpvars();
  end

  initial
  begin
    topclk = 0;
    sig1 = 0;
    sig2 = 0;
    WEIGHTBIAS_EN = 0;
    #10
     WEIGHTBIAS_EN = 1;
    #10
     WEIGHTBIAS_EN = 0;
    #100
     sig1 = 16'h0d29;
    sig2 = 16'hf054;
    #2000
     sig1 = 0;
    sig2 = 0;
    #2000

     $finish;
  end

endmodule

Vivado-Project/NeuralNetwork/NeuralNetwork.sim/sim_1/behav/xsim/dump.vcd
$date
   Fri May  5 10:51:02 2023
$end
$version
  2022.2
$end
$timescale
  1ps
$end
$scope module TDNN_TB $end
$var reg 16 ! sig1 [15:0] $end
$var reg 16 " sig2 [15:0] $end
$var reg 1 # topclk $end
$var reg 1 $ WEIGHTBIAS_EN $end
$var wire 16 % out1 [15:0] $end
$var wire 16 & out2 [15:0] $end
$scope module DUT $end
$var wire 16 ' SIG_IN1 [15:0] $end
$var wire 16 ( SIG_IN2 [15:0] $end
$var wire 1 ) CLOCK_N $end
$var wire 1 * wb_en $end
$var wire 16 % SIG_OUT1 [15:0] $end
$var wire 16 & SIG_OUT2 [15:0] $end
$var wire 16 + delay_out_1 [15:0] $end
$var wire 16 , delay_out_2 [15:0] $end
$var wire 16 - delay_out_3 [15:0] $end
$var wire 16 . delay_out_4 [15:0] $end
$var wire 16 / delay_out_5 [15:0] $end
$var wire 16 0 delay_out_6 [15:0] $end
$var wire 16 1 delay_out_7 [15:0] $end
$var wire 16 2 delay_out_8 [15:0] $end
$var wire 20 3 n1_out [19:0] $end
$var wire 20 4 n2_out [19:0] $end
$var wire 20 5 n3_out [19:0] $end
$var wire 20 6 n4_out [19:0] $end
$var wire 20 7 n5_out [19:0] $end
$var wire 20 8 n6_out [19:0] $end
$var wire 20 9 n7_out [19:0] $end
$var wire 20 : n8_out [19:0] $end
$var wire 20 ; n9_out [19:0] $end
$var wire 20 < n10_out [19:0] $end
$var wire 16 = n11_out [15:0] $end
$var wire 16 > n12_out [15:0] $end
$scope module delay1 $end
$var wire 16 ' INPUT [15:0] $end
$var wire 1 ) CLK_N $end
$var reg 16 ? DELAY_OUTPUT [15:0] $end
$var reg 16 @ TEMP_HOLD [15:0] $end
$upscope $end
$scope module delay2 $end
$var wire 16 + INPUT [15:0] $end
$var wire 1 ) CLK_N $end
$var reg 16 A DELAY_OUTPUT [15:0] $end
$var reg 16 B TEMP_HOLD [15:0] $end
$upscope $end
$scope module delay3 $end
$var wire 16 , INPUT [15:0] $end
$var wire 1 ) CLK_N $end
$var reg 16 C DELAY_OUTPUT [15:0] $end
$var reg 16 D TEMP_HOLD [15:0] $end
$upscope $end
$scope module delay4 $end
$var wire 16 - INPUT [15:0] $end
$var wire 1 ) CLK_N $end
$var reg 16 E DELAY_OUTPUT [15:0] $end
$var reg 16 F TEMP_HOLD [15:0] $end
$upscope $end
$scope module delay5 $end
$var wire 16 ( INPUT [15:0] $end
$var wire 1 ) CLK_N $end
$var reg 16 G DELAY_OUTPUT [15:0] $end
$var reg 16 H TEMP_HOLD [15:0] $end
$upscope $end
$scope module delay6 $end
$var wire 16 / INPUT [15:0] $end
$var wire 1 ) CLK_N $end
$var reg 16 I DELAY_OUTPUT [15:0] $end
$var reg 16 J TEMP_HOLD [15:0] $end
$upscope $end
$scope module delay7 $end
$var wire 16 0 INPUT [15:0] $end
$var wire 1 ) CLK_N $end
$var reg 16 K DELAY_OUTPUT [15:0] $end
$var reg 16 L TEMP_HOLD [15:0] $end
$upscope $end
$scope module delay8 $end
$var wire 16 1 INPUT [15:0] $end
$var wire 1 ) CLK_N $end
$var reg 16 M DELAY_OUTPUT [15:0] $end
$var reg 16 N TEMP_HOLD [15:0] $end
$upscope $end
$scope module neuron1 $end
$var wire 1 * WB_EN $end
$var wire 16 O BIAS_IN [15:0] $end
$var wire 1 ) CLOCK_N $end
$var reg 20 P NEURON_OUT [19:0] $end
$var reg 16 Q bias [15:0] $end
$var reg 20 R addition [19:0] $end
$var integer 32 S i [31:0] $end
$upscope $end
$scope module neuron2 $end
$var wire 1 * WB_EN $end
$var wire 16 T BIAS_IN [15:0] $end
$var wire 1 ) CLOCK_N $end
$var reg 20 U NEURON_OUT [19:0] $end
$var reg 16 V bias [15:0] $end
$var reg 20 W addition [19:0] $end
$var integer 32 X i [31:0] $end
$upscope $end
$scope module neuron3 $end
$var wire 1 * WB_EN $end
$var wire 16 Y BIAS_IN [15:0] $end
$var wire 1 ) CLOCK_N $end
$var reg 20 Z NEURON_OUT [19:0] $end
$var reg 16 [ bias [15:0] $end
$var reg 20 \ addition [19:0] $end
$var integer 32 ] i [31:0] $end
$upscope $end
$scope module neuron4 $end
$var wire 1 * WB_EN $end
$var wire 16 ^ BIAS_IN [15:0] $end
$var wire 1 ) CLOCK_N $end
$var reg 20 _ NEURON_OUT [19:0] $end
$var reg 16 ` bias [15:0] $end
$var reg 20 a addition [19:0] $end
$var integer 32 b i [31:0] $end
$upscope $end
$scope module neuron5 $end
$var wire 1 * WB_EN $end
$var wire 16 c BIAS_IN [15:0] $end
$var wire 1 ) CLOCK_N $end
$var reg 20 d NEURON_OUT [19:0] $end
$var reg 16 e bias [15:0] $end
$var reg 20 f addition [19:0] $end
$var integer 32 g i [31:0] $end
$upscope $end
$scope module neuron6 $end
$var wire 1 * WB_EN $end
$var wire 16 h BIAS_IN [15:0] $end
$var wire 1 ) CLOCK_N $end
$var reg 20 i NEURON_OUT [19:0] $end
$var reg 16 j bias [15:0] $end
$var reg 20 k addition [19:0] $end
$var integer 32 l i [31:0] $end
$upscope $end
$scope module neuron7 $end
$var wire 1 * WB_EN $end
$var wire 16 m BIAS_IN [15:0] $end
$var wire 1 ) CLOCK_N $end
$var reg 20 n NEURON_OUT [19:0] $end
$var reg 16 o bias [15:0] $end
$var reg 20 p addition [19:0] $end
$var integer 32 q i [31:0] $end
$upscope $end
$scope module neuron8 $end
$var wire 1 * WB_EN $end
$var wire 16 r BIAS_IN [15:0] $end
$var wire 1 ) CLOCK_N $end
$var reg 20 s NEURON_OUT [19:0] $end
$var reg 16 t bias [15:0] $end
$var reg 20 u addition [19:0] $end
$var integer 32 v i [31:0] $end
$upscope $end
$scope module neuron9 $end
$var wire 1 * WB_EN $end
$var wire 16 w BIAS_IN [15:0] $end
$var wire 1 ) CLOCK_N $end
$var reg 20 x NEURON_OUT [19:0] $end
$var reg 16 y bias [15:0] $end
$var reg 20 z addition [19:0] $end
$var integer 32 { i [31:0] $end
$upscope $end
$scope module neuron10 $end
$var wire 1 * WB_EN $end
$var wire 16 | BIAS_IN [15:0] $end
$var wire 1 ) CLOCK_N $end
$var reg 20 } NEURON_OUT [19:0] $end
$var reg 16 ~ bias [15:0] $end
$var reg 20 !! addition [19:0] $end
$var integer 32 "! i [31:0] $end
$upscope $end
$scope module sigAct $end
$upscope $end
$scope module neuron11 $end
$var wire 1 * WB_EN $end
$var wire 16 #! BIAS_IN [15:0] $end
$var wire 1 ) CLOCK_N $end
$var reg 16 $! NEURON_OUT [15:0] $end
$var reg 16 %! bias [15:0] $end
$var reg 20 &! addition [19:0] $end
$var reg 1 '! sigmoid_flag $end
$var integer 32 (! i [31:0] $end
$scope module activation $end
$var wire 20 )! x [19:0] $end
$var reg 16 $! y [15:0] $end
$upscope $end
$upscope $end
$scope module neuron12 $end
$var wire 1 * WB_EN $end
$var wire 16 *! BIAS_IN [15:0] $end
$var wire 1 ) CLOCK_N $end
$var reg 16 +! NEURON_OUT [15:0] $end
$var reg 16 ,! bias [15:0] $end
$var reg 20 -! addition [19:0] $end
$var reg 1 .! sigmoid_flag $end
$var integer 32 /! i [31:0] $end
$scope module activation $end
$var wire 20 0! x [19:0] $end
$var reg 16 +! y [15:0] $end
$upscope $end
$upscope $end
$upscope $end
$upscope $end
$enddefinitions $end
#0
$dumpvars
b0 !
b0 !!
b0 "
b1010 "!
0#
b10010001000000 #!
0$
b0 $!
b0 %
bx %!
b0 &
b0 &!
b0 '
0'!
b0 (
b1010 (!
0)
b0 )!
0*
b1110110100010111 *!
b0 +
b0 +!
b0 ,
bx ,!
b0 -
b0 -!
b0 .
0.!
b0 /
b1010 /!
b0 0
b0 0!
b0 1
b0 2
b0 3
b0 4
b0 5
b0 6
b0 7
b0 8
b0 9
b0 :
b0 ;
b0 <
bz =
bz >
b0 ?
b0 @
b0 A
bx B
b0 C
bx D
b0 E
bx F
b0 G
b0 H
b0 I
bx J
b0 K
bx L
b0 M
bx N
b101000011110 O
b0 P
bx Q
b0 R
b1010 S
b1110001110001111 T
b0 U
bx V
b0 W
b1010 X
b1111001101101011 Y
b0 Z
bx [
b0 \
b1010 ]
b1111001110111011 ^
b0 _
bx `
b0 a
b1010 b
b1101100110101110 c
b0 d
bx e
b0 f
b1010 g
b110001111111 h
b0 i
bx j
b0 k
b1010 l
b1101110000110010 m
b0 n
bx o
b0 p
b1010 q
b1110111011010110 r
b0 s
bx t
b0 u
b1010 v
b1110111110000000 w
b0 x
bx y
b0 z
b1010 {
b1111001010001010 |
b0 }
bx ~
$end
#5000
1#
1)
#10000
bx !!
b1010 "!
0#
1$
bx $!
bx %
b10010001000000 %!
bx &
bx &!
b1010 (!
0)
bx )!
1*
bx +!
bx ,
b1110110100010111 ,!
bx -
bx -!
bx .
b1010 /!
bx 0
bx 0!
bx 1
bx 2
bx 3
bx 4
bx 5
bx 6
bx 7
bx 8
bx 9
bx :
bx ;
bx <
b0 ?
b0 @
bx A
b0 B
bx C
b0 D
bx E
b0 F
b0 G
b0 H
bx I
b0 J
bx K
b0 L
bx M
b0 N
bx P
b101000011110 Q
bx R
b1010 S
bx U
b1110001110001111 V
bx W
b1010 X
bx Z
b1111001101101011 [
bx \
b1010 ]
bx _
b1111001110111011 `
bx a
b1010 b
bx d
b1101100110101110 e
bx f
b1010 g
bx i
b110001111111 j
bx k
b1010 l
bx n
b1101110000110010 o
bx p
b1010 q
bx s
b1110111011010110 t
bx u
b1010 v
bx x
b1110111110000000 y
bx z
b1010 {
bx }
b1111001010001010 ~
#15000
1#
1)
#20000
bx !!
b1010 "!
0#
0$
bx &!
b1010 (!
0)
bx )!
0*
b0 ,
b0 -
bx -!
b0 .
b1010 /!
b0 0
bx 0!
b0 1
b0 2
b0 ?
b0 @
b0 A
b0 B
b0 C
bx D
b0 E
bx F
b0 G
b0 H
b0 I
b0 J
b0 K
bx L
b0 M
bx N
bx P
bx R
b1010 S
bx U
bx W
b1010 X
bx Z
bx \
b1010 ]
bx _
bx a
b1010 b
bx d
bx f
b1010 g
bx i
bx k
b1010 l
bx n
bx p
b1010 q
bx s
bx u
b1010 v
bx x
bx z
b1010 {
bx }
#25000
1#
1)
#30000
bx !!
b1010 "!
0#
bx &!
b1010 (!
0)
bx )!
bx -
bx -!
bx .
b1010 /!
bx 0!
bx 1
bx 2
b0 ?
b0 @
b0 A
b0 B
bx C
b0 D
bx E
b0 F
b0 G
b0 H
b0 I
b0 J
bx K
b0 L
bx M
b0 N
bx P
bx R
b1010 S
bx U
bx W
b1010 X
bx Z
bx \
b1010 ]
bx _
bx a
b1010 b
bx d
bx f
b1010 g
bx i
bx k
b1010 l
bx n
bx p
b1010 q
bx s
bx u
b1010 v
bx x
bx z
b1010 {
bx }
#35000
1#
1)
#40000
b11111111001010001010 !!
b1010 "!
0#
bx &!
b1010 (!
0)
bx )!
b0 -
bx -!
b0 .
b1010 /!
bx 0!
b0 1
b0 2
b101000011110 3
b11111110001110001111 4
b11111111001101101011 5
b11111111001110111011 6
b11111101100110101110 7
b110001111111 8
b11111101110000110010 9
b11111110111011010110 :
b11111110111110000000 ;
b11111111001010001010 <
b0 ?
b0 @
b0 A
b0 B
b0 C
b0 D
b0 E
bx F
b0 G
b0 H
b0 I
b0 J
b0 K
b0 L
b0 M
bx N
b101000011110 P
b101000011110 R
b1010 S
b11111110001110001111 U
b11111110001110001111 W
b1010 X
b11111111001101101011 Z
b11111111001101101011 \
b1010 ]
b11111111001110111011 _
b11111111001110111011 a
b1010 b
b11111101100110101110 d
b11111101100110101110 f
b1010 g
b110001111111 i
b110001111111 k
b1010 l
b11111101110000110010 n
b11111101110000110010 p
b1010 q
b11111110111011010110 s
b11111110111011010110 u
b1010 v
b11111110111110000000 x
b11111110111110000000 z
b1010 {
b11111111001010001010 }
#45000
1#
1)
#50000
bx !!
b1010 "!
0#
bx &!
b1010 (!
0)
bx )!
bx -!
bx .
b1010 /!
bx 0!
bx 2
bx 3
bx 4
bx 5
bx 6
bx 7
bx 8
bx 9
bx :
bx ;
bx <
b0 ?
b0 @
b0 A
b0 B
b0 C
b0 D
bx E
b0 F
b0 G
b0 H
b0 I
b0 J
b0 K
b0 L
bx M
b0 N
bx P
bx R
b1010 S
bx U
bx W
b1010 X
bx Z
bx \
b1010 ]
bx _
bx a
b1010 b
bx d
bx f
b1010 g
bx i
bx k
b1010 l
bx n
bx p
b1010 q
bx s
bx u
b1010 v
bx x
bx z
b1010 {
bx }
#55000
1#
1)
#60000
b11111111001010001010 !!
b1010 "!
0#
b100000111 $!
b100000111 %
b1111111100100001 &
b1100000000100000111 &!
b1010 (!
0)
b1100000000100000111 )!
b1111111100100001 +!
b111111111100100001 -!
b0 .
b1010 /!
b111111111100100001 0!
b0 2
b101000011110 3
b11111110001110001111 4
b11111111001101101011 5
b11111111001110111011 6
b11111101100110101110 7
b110001111111 8
b11111101110000110010 9
b11111110111011010110 :
b11111110111110000000 ;
b11111111001010001010 <
b0 ?
b0 @
b0 A
b0 B
b0 C
b0 D
b0 E
b0 F
b0 G
b0 H
b0 I
b0 J
b0 K
b0 L
b0 M
b0 N
b101000011110 P
b101000011110 R
b1010 S
b11111110001110001111 U
b11111110001110001111 W
b1010 X
b11111111001101101011 Z
b11111111001101101011 \
b1010 ]
b11111111001110111011 _
b11111111001110111011 a
b1010 b
b11111101100110101110 d
b11111101100110101110 f
b1010 g
b110001111111 i
b110001111111 k
b1010 l
b11111101110000110010 n
b11111101110000110010 p
b1010 q
b11111110111011010110 s
b11111110111011010110 u
b1010 v
b11111110111110000000 x
b11111110111110000000 z
b1010 {
b11111111001010001010 }
#65000
1#
1)
#70000
bx !!
b1010 "!
0#
bx $!
bx %
bx &
bx &!
b1010 (!
0)
bx )!
bx +!
bx -!
b1010 /!
bx 0!
bx 3
bx 4
bx 5
bx 6
bx 7
bx 8
bx 9
bx :
bx ;
bx <
b0 ?
b0 @
b0 A
b0 B
b0 C
b0 D
b0 E
b0 F
b0 G
b0 H
b0 I
b0 J
b0 K
b0 L
b0 M
b0 N
bx P
bx R
b1010 S
bx U
bx W
b1010 X
bx Z
bx \
b1010 ]
bx _
bx a
b1010 b
bx d
bx f
b1010 g
bx i
bx k
b1010 l
bx n
bx p
b1010 q
bx s
bx u
b1010 v
bx x
bx z
b1010 {
bx }
#75000
1#
1)
